CONTRIBUTORS.txt
MANIFEST.in
README.txt
setup.cfg
setup.py
Paste-1.7.5.1-py2.6.egg/EGG-INFO/SOURCES.txt
Paste-1.7.5.1-py2.6.egg/EGG-INFO/dependency_links.txt
Paste-1.7.5.1-py2.6.egg/EGG-INFO/entry_points.txt
Paste-1.7.5.1-py2.6.egg/EGG-INFO/namespace_packages.txt
Paste-1.7.5.1-py2.6.egg/EGG-INFO/requires.txt
Paste-1.7.5.1-py2.6.egg/EGG-INFO/top_level.txt
Paste-1.7.5.1-py2.6.egg/paste/__init__.py
Paste-1.7.5.1-py2.6.egg/paste/cascade.py
Paste-1.7.5.1-py2.6.egg/paste/cgiapp.py
Paste-1.7.5.1-py2.6.egg/paste/cgitb_catcher.py
Paste-1.7.5.1-py2.6.egg/paste/config.py
Paste-1.7.5.1-py2.6.egg/paste/errordocument.py
Paste-1.7.5.1-py2.6.egg/paste/fileapp.py
Paste-1.7.5.1-py2.6.egg/paste/fixture.py
Paste-1.7.5.1-py2.6.egg/paste/flup_session.py
Paste-1.7.5.1-py2.6.egg/paste/gzipper.py
Paste-1.7.5.1-py2.6.egg/paste/httpexceptions.py
Paste-1.7.5.1-py2.6.egg/paste/httpheaders.py
Paste-1.7.5.1-py2.6.egg/paste/httpserver.py
Paste-1.7.5.1-py2.6.egg/paste/lint.py
Paste-1.7.5.1-py2.6.egg/paste/modpython.py
Paste-1.7.5.1-py2.6.egg/paste/pony.py
Paste-1.7.5.1-py2.6.egg/paste/progress.py
Paste-1.7.5.1-py2.6.egg/paste/proxy.py
Paste-1.7.5.1-py2.6.egg/paste/recursive.py
Paste-1.7.5.1-py2.6.egg/paste/registry.py
Paste-1.7.5.1-py2.6.egg/paste/reloader.py
Paste-1.7.5.1-py2.6.egg/paste/request.py
Paste-1.7.5.1-py2.6.egg/paste/response.py
Paste-1.7.5.1-py2.6.egg/paste/session.py
Paste-1.7.5.1-py2.6.egg/paste/transaction.py
Paste-1.7.5.1-py2.6.egg/paste/translogger.py
Paste-1.7.5.1-py2.6.egg/paste/url.py
Paste-1.7.5.1-py2.6.egg/paste/urlmap.py
Paste-1.7.5.1-py2.6.egg/paste/urlparser.py
Paste-1.7.5.1-py2.6.egg/paste/wsgilib.py
Paste-1.7.5.1-py2.6.egg/paste/wsgiwrappers.py
Paste-1.7.5.1-py2.6.egg/paste/auth/__init__.py
Paste-1.7.5.1-py2.6.egg/paste/auth/auth_tkt.py
Paste-1.7.5.1-py2.6.egg/paste/auth/basic.py
Paste-1.7.5.1-py2.6.egg/paste/auth/cas.py
Paste-1.7.5.1-py2.6.egg/paste/auth/cookie.py
Paste-1.7.5.1-py2.6.egg/paste/auth/digest.py
Paste-1.7.5.1-py2.6.egg/paste/auth/form.py
Paste-1.7.5.1-py2.6.egg/paste/auth/grantip.py
Paste-1.7.5.1-py2.6.egg/paste/auth/multi.py
Paste-1.7.5.1-py2.6.egg/paste/auth/open_id.py
Paste-1.7.5.1-py2.6.egg/paste/cowbell/__init__.py
Paste-1.7.5.1-py2.6.egg/paste/debug/__init__.py
Paste-1.7.5.1-py2.6.egg/paste/debug/debugapp.py
PasteDeploy-1.5.0-py2.6.egg/EGG-INFO/SOURCES.txt
PasteDeploy-1.5.0-py2.6.egg/EGG-INFO/dependency_links.txt
PasteDeploy-1.5.0-py2.6.egg/EGG-INFO/entry_points.txt
PasteDeploy-1.5.0-py2.6.egg/EGG-INFO/namespace_packages.txt
PasteDeploy-1.5.0-py2.6.egg/EGG-INFO/requires.txt
PasteDeploy-1.5.0-py2.6.egg/EGG-INFO/top_level.txt
PasteScript-1.7.5-py2.6.egg/EGG-INFO/SOURCES.txt
PasteScript-1.7.5-py2.6.egg/EGG-INFO/dependency_links.txt
PasteScript-1.7.5-py2.6.egg/EGG-INFO/entry_points.txt
PasteScript-1.7.5-py2.6.egg/EGG-INFO/namespace_packages.txt
PasteScript-1.7.5-py2.6.egg/EGG-INFO/requires.txt
PasteScript-1.7.5-py2.6.egg/EGG-INFO/top_level.txt
collective.localrolespanel.egg-info/PKG-INFO
collective.localrolespanel.egg-info/SOURCES.txt
collective.localrolespanel.egg-info/dependency_links.txt
collective.localrolespanel.egg-info/entry_points.txt
collective.localrolespanel.egg-info/namespace_packages.txt
collective.localrolespanel.egg-info/not-zip-safe
collective.localrolespanel.egg-info/paster_plugins.txt
collective.localrolespanel.egg-info/requires.txt
collective.localrolespanel.egg-info/top_level.txt
