Metadata-Version: 1.0
Name: collective.localrolespanel
Version: 0.2
Summary: Adds a controlpanel to the site to edit local role settings using csv
Home-page: https://github.com/collective/collective.localrolespanel
Author: Hans-Peter Locher
Author-email: hans-peter.locher@inquant.de
License: GPL
Platform: UNKNOWN
Classifier: Framework :: Plone
Classifier: Intended Audience :: Developers
Classifier: License :: OSI Approved :: GNU General Public License (GPL)
